djungarik/__init__.py
djungarik/main.py
djungarik/widgets.py
djungarik/window.py
djungarik-0.1.3.dist-info/LICENSE
djungarik-0.1.3.dist-info/METADATA
djungarik-0.1.3.dist-info/WHEEL
djungarik-0.1.3.dist-info/top_level.txt
djungarik-0.1.3.dist-info/RECORD
