Metadata-Version: 2.1
Name: djungarik
Version: 0.1.3
Summary: Djungarik — A simple Tkinter-based UI package
Home-page: https://github.com/djungarikDEV/djungarik
Author: djungar_DEV
Author-email: arnispprt@gmail.com
Classifier: Programming Language :: Python :: 3
Classifier: Operating System :: OS Independent
License-File: LICENSE
